securid/__init__.py
securid/cli.py
securid/exceptions.py
securid/jsontoken.py
securid/sdtid.py
securid/stoken.py
securid/token.py
securid/utils.py
securid-0.9.8.dist-info/LICENSE
securid-0.9.8.dist-info/METADATA
securid-0.9.8.dist-info/WHEEL
securid-0.9.8.dist-info/entry_points.txt
securid-0.9.8.dist-info/top_level.txt
securid-0.9.8.dist-info/zip-safe
securid-0.9.8.dist-info/RECORD
