Metadata-Version: 2.2
Name: securid
Version: 0.9.8
Summary: Python RSA SecurID 128-bit compatible library
Home-page: http://github.com/andreax79/python-securid
Author: Andrea Bonomi
Author-email: andrea.bonomi@gmail.com
License: MIT
Project-URL: Bug Tracker, http://github.com/andreax79/python-securid/issues
Project-URL: Source Code, http://github.com/andreax79/python-securid
Keywords: securid,otp
Platform: any
Classifier: Development Status :: 5 - Production/Stable
Classifier: Environment :: Console
Classifier: Intended Audience :: Developers
Classifier: License :: OSI Approved :: MIT License
Classifier: Operating System :: OS Independent
Classifier: Programming Language :: Python
Classifier: Topic :: Utilities
Classifier: Topic :: Software Development :: Libraries :: Python Modules
Classifier: Programming Language :: Python :: 3.5
Classifier: Programming Language :: Python :: 3.6
Classifier: Programming Language :: Python :: 3.7
Classifier: Programming Language :: Python :: 3.8
Classifier: Programming Language :: Python :: 3.9
Classifier: Programming Language :: Python :: 3.10
Classifier: Programming Language :: Python :: 3.11
Classifier: Programming Language :: Python :: 3.12
Classifier: Programming Language :: Python :: 3.13
Classifier: Programming Language :: Python :: 3.14
Requires-Python: >=3.5
License-File: LICENSE
Requires-Dist: cryptography>=36
Provides-Extra: test
Requires-Dist: pytest; extra == "test"
